einops_exts/__init__.py
einops_exts/einops_exts.py
einops_exts/torch.py
einops_exts-0.0.4.dist-info/LICENSE
einops_exts-0.0.4.dist-info/METADATA
einops_exts-0.0.4.dist-info/WHEEL
einops_exts-0.0.4.dist-info/top_level.txt
einops_exts-0.0.4.dist-info/RECORD
